[
  {
    "id": 2000,
    "name": "Кофемашина двухгруппная",
    "category": "Кофемашины и кофемолки",
    "brand": "La Marzocco",
    "model": "Linea PB 2GR",
    "price_pln": 52000,
    "supplier": "Coffee Solutions Polska",
    "image": null,
    "specs": "2 группы, PID-контроль, встроенные весы, объём бойлера 7 л"
  },
  {
    "id": 2001,
    "name": "Кофемашина двухгруппная",
    "category": "Кофемашины и кофемолки",
    "brand": "Victoria Arduino",
    "model": "Eagle One 2GR",
    "price_pln": 48000,
    "supplier": "Coffee Solutions Polska",
    "image": null,
    "specs": "2 группы, система NEO, энергосбережение до 25%, T3 технология"
  },
  {
    "id": 2002,
    "name": "Кофемашина однагруппная",
    "category": "Кофемашины и кофемолки",
    "brand": "La Marzocco",
    "model": "GS3 MP",
    "price_pln": 32000,
    "supplier": "Coffee Solutions Polska",
    "image": null,
    "specs": "1 группа, механические паддлы, двойной бойлер, для малых объёмов"
  },
  {
    "id": 2003,
    "name": "Кофемашина трёхгруппная",
    "category": "Кофемашины и кофемолки",
    "brand": "Nuova Simonelli",
    "model": "Aurelia Wave T3 3GR",
    "price_pln": 45000,
    "supplier": "Gastro-Serwis",
    "image": null,
    "specs": "3 группы, технология T3, Soft Infusion System, высокая производительность"
  },
  {
    "id": 2004,
    "name": "Кофемашина двухгруппная компактная",
    "category": "Кофемашины и кофемолки",
    "brand": "Nuova Simonelli",
    "model": "Oscar II 2GR",
    "price_pln": 12500,
    "supplier": "Gastro-Serwis",
    "image": null,
    "specs": "2 группы, теплообменник, компактная для малых помещений"
  },
  {
    "id": 2005,
    "name": "Кофемашина суперавтомат",
    "category": "Кофемашины и кофемолки",
    "brand": "Nuova Simonelli",
    "model": "Prontobar Touch",
    "price_pln": 28000,
    "supplier": "Gastro-Serwis",
    "image": null,
    "specs": "Суперавтомат, сенсорный дисплей, 2 кофемолки, до 200 чашек/день"
  },
  {
    "id": 2006,
    "name": "Кофемолка для эспрессо",
    "category": "Кофемашины и кофемолки",
    "brand": "Mahlkonig",
    "model": "E65S GbW",
    "price_pln": 9800,
    "supplier": "Coffee Solutions Polska",
    "image": null,
    "specs": "Жернова 65 мм, Grind by Weight, дисплей, скорость 2.2 г/с"
  },
  {
    "id": 2007,
    "name": "Кофемолка для эспрессо",
    "category": "Кофемашины и кофемолки",
    "brand": "Eureka",
    "model": "Atom Specialty 75",
    "price_pln": 6200,
    "supplier": "Coffee Solutions Polska",
    "image": null,
    "specs": "Жернова 75 мм, бесступенчатая регулировка, тихая работа 64 дБ"
  },
  {
    "id": 2008,
    "name": "Кофемолка для эспрессо",
    "category": "Кофемашины и кофемолки",
    "brand": "Mahlkonig",
    "model": "K30 Vario",
    "price_pln": 7500,
    "supplier": "Coffee Solutions Polska",
    "image": null,
    "specs": "Жернова 65 мм, twin hopper, таймер дозирования, 1400 об/мин"
  },
  {
    "id": 2009,
    "name": "Кофемолка для фильтра",
    "category": "Кофемашины и кофемолки",
    "brand": "Mahlkonig",
    "model": "EK43 S",
    "price_pln": 11500,
    "supplier": "Coffee Solutions Polska",
    "image": null,
    "specs": "Жернова 98 мм, универсальный помол, для фильтра и эспрессо"
  },
  {
    "id": 2010,
    "name": "Кофемолка для фильтра",
    "category": "Кофемашины и кофемолки",
    "brand": "Eureka",
    "model": "Zenith 65 E",
    "price_pln": 4800,
    "supplier": "Coffee Solutions Polska",
    "image": null,
    "specs": "Жернова 65 мм, электронная дозировка, High Speed 1350 об/мин"
  },
  {
    "id": 2011,
    "name": "Фильтр-кофеварка проточная",
    "category": "Кофемашины и кофемолки",
    "brand": "Bravilor",
    "model": "Mondo Twin",
    "price_pln": 3200,
    "supplier": "Gastro-Serwis",
    "image": null,
    "specs": "Двойная станция, подключение к водопроводу, 18 л/ч"
  },
  {
    "id": 2012,
    "name": "Фильтр-кофеварка наливная",
    "category": "Кофемашины и кофемолки",
    "brand": "Bravilor",
    "model": "Novo 2",
    "price_pln": 1800,
    "supplier": "Gastro-Serwis",
    "image": null,
    "specs": "Наливная, 2 термоса по 1.7 л, индикатор готовности"
  },
  {
    "id": 2013,
    "name": "Темпер автоматический",
    "category": "Посуда и аксессуары",
    "brand": "Puqpress",
    "model": "M5",
    "price_pln": 5500,
    "supplier": "Coffee Solutions Polska",
    "image": null,
    "specs": "Автоматическое трамбование 10-30 кг, совместимость с портафильтрами 58 мм"
  },
  {
    "id": 2014,
    "name": "Набор бариста",
    "category": "Посуда и аксессуары",
    "brand": "Hario",
    "model": "V60 Pro Kit",
    "price_pln": 850,
    "supplier": "Coffee Solutions Polska",
    "image": null,
    "specs": "Дриппер V60-02, сервер 600 мл, мерная ложка, 100 фильтров"
  },
  {
    "id": 2015,
    "name": "Кемекс",
    "category": "Посуда и аксессуары",
    "brand": "Chemex",
    "model": "Classic 6 Cup",
    "price_pln": 280,
    "supplier": "Coffee Solutions Polska",
    "image": null,
    "specs": "6 чашек (880 мл), стекло боросиликатное, деревянный воротник"
  },
  {
    "id": 2016,
    "name": "Чайник для пуровера",
    "category": "Посуда и аксессуары",
    "brand": "Hario",
    "model": "Buono V60 Drip Kettle Electric",
    "price_pln": 580,
    "supplier": "Coffee Solutions Polska",
    "image": null,
    "specs": "Электрический, гусиная шея, объём 0.8 л, контроль температуры"
  },
  {
    "id": 2017,
    "name": "Весы бариста",
    "category": "Посуда и аксессуары",
    "brand": "Acaia",
    "model": "Pearl S",
    "price_pln": 1200,
    "supplier": "Coffee Solutions Polska",
    "image": null,
    "specs": "0.1 г точность, таймер, Bluetooth, водонепроницаемые IP65"
  },
  {
    "id": 2018,
    "name": "Питчер для молока",
    "category": "Посуда и аксессуары",
    "brand": "Motta",
    "model": "Europa 500 мл",
    "price_pln": 120,
    "supplier": "Gastro-Serwis",
    "image": null,
    "specs": "Нержавейка 18/10, 500 мл, носик для латте-арта"
  },
  {
    "id": 2019,
    "name": "Питчер для молока",
    "category": "Посуда и аксессуары",
    "brand": "Motta",
    "model": "Europa 350 мл",
    "price_pln": 95,
    "supplier": "Gastro-Serwis",
    "image": null,
    "specs": "Нержавейка 18/10, 350 мл, для капучино"
  },
  {
    "id": 2020,
    "name": "Нок-бокс",
    "category": "Посуда и аксессуары",
    "brand": "Cafelat",
    "model": "Tubbi Large",
    "price_pln": 350,
    "supplier": "Coffee Solutions Polska",
    "image": null,
    "specs": "ABS пластик, сменная планка, объём для ~50 порций"
  },
  {
    "id": 2021,
    "name": "Дистрибьютор кофе",
    "category": "Посуда и аксессуары",
    "brand": "ONA Coffee",
    "model": "OCD V3 58.5 мм",
    "price_pln": 450,
    "supplier": "Coffee Solutions Polska",
    "image": null,
    "specs": "Нержавейка, регулировка глубины, 58.5 мм"
  },
  {
    "id": 2022,
    "name": "Холодильный шкаф барный",
    "category": "Холодильное оборудование",
    "brand": "Liebherr",
    "model": "FKvsl 3613 Premium",
    "price_pln": 8500,
    "supplier": "Gastro-Serwis",
    "image": null,
    "specs": "335 л, стеклянная дверь, +1...+15°C, LED освещение, R600a"
  },
  {
    "id": 2023,
    "name": "Холодильный шкаф двухдверный",
    "category": "Холодильное оборудование",
    "brand": "True",
    "model": "T-49-HC",
    "price_pln": 14500,
    "supplier": "Gastro-Serwis",
    "image": null,
    "specs": "1388 л, 2 двери, нержавейка, +0.5...+4°C, R290"
  },
  {
    "id": 2024,
    "name": "Стол холодильный",
    "category": "Холодильное оборудование",
    "brand": "True",
    "model": "TWT-48SD-HC",
    "price_pln": 11000,
    "supplier": "Gastro-Serwis",
    "image": null,
    "specs": "2 двери, рабочая поверхность нержавейка, +0.5...+4°C, 340 л"
  },
  {
    "id": 2025,
    "name": "Морозильный ларь",
    "category": "Холодильное оборудование",
    "brand": "Liebherr",
    "model": "GTP 2356 Premium",
    "price_pln": 5200,
    "supplier": "Gastro-Serwis",
    "image": null,
    "specs": "200 л, StopFrost, -14...-28°C, энергокласс A+++"
  },
  {
    "id": 2026,
    "name": "Льдогенератор кубикового льда",
    "category": "Холодильное оборудование",
    "brand": "Brema",
    "model": "CB 416A",
    "price_pln": 6800,
    "supplier": "Gastro-Serwis",
    "image": null,
    "specs": "42 кг/сутки, бункер 16 кг, кубики 18 г, воздушное охлаждение"
  },
  {
    "id": 2027,
    "name": "Витрина кондитерская холодильная",
    "category": "Витрины и прилавки",
    "brand": "Tecfrigo",
    "model": "Prisma 100 TNV",
    "price_pln": 9500,
    "supplier": "Gastro-Serwis",
    "image": null,
    "specs": "1000 мм, гнутое стекло, LED, +4...+10°C, 3 полки"
  },
  {
    "id": 2028,
    "name": "Витрина кондитерская настольная",
    "category": "Витрины и прилавки",
    "brand": "Tecfrigo",
    "model": "Snelle 350 TNV",
    "price_pln": 5800,
    "supplier": "Gastro-Serwis",
    "image": null,
    "specs": "700 мм, настольная, +2...+8°C, 2 полки, стеклопакет"
  },
  {
    "id": 2029,
    "name": "Витрина тепловая настольная",
    "category": "Витрины и прилавки",
    "brand": "Roller Grill",
    "model": "WD 780 SN",
    "price_pln": 3200,
    "supplier": "Gastro-Serwis",
    "image": null,
    "specs": "780 мм, +30...+90°C, влажность, LED подсветка, 3 уровня"
  },
  {
    "id": 2030,
    "name": "Блендер профессиональный",
    "category": "Оборудование для кухни",
    "brand": "Vitamix",
    "model": "Quiet One",
    "price_pln": 7800,
    "supplier": "Coffee Solutions Polska",
    "image": null,
    "specs": "1400 Вт, шумоизоляция, 6 программ, для смузи и фраппе, 1.4 л"
  },
  {
    "id": 2031,
    "name": "Блендер погружной",
    "category": "Оборудование для кухни",
    "brand": "Robot Coupe",
    "model": "CMP 300 V.V.",
    "price_pln": 2400,
    "supplier": "Gastro-Serwis",
    "image": null,
    "specs": "350 Вт, длина штанги 300 мм, плавная регулировка скорости"
  },
  {
    "id": 2032,
    "name": "Тостер конвейерный",
    "category": "Оборудование для кухни",
    "brand": "Hatco",
    "model": "TQ-10",
    "price_pln": 4200,
    "supplier": "Gastro-Serwis",
    "image": null,
    "specs": "300 тостов/ч, конвейерный, кварцевые нагреватели, таймер"
  },
  {
    "id": 2033,
    "name": "Печь конвекционная компактная",
    "category": "Оборудование для кухни",
    "brand": "Unox",
    "model": "BAKERLUX SPEED.Pro XESW-03HS-EDDN",
    "price_pln": 15000,
    "supplier": "Gastro-Serwis",
    "image": null,
    "specs": "3 противня 460x330, пароконвекция, сенсорное управление, для выпечки"
  },
  {
    "id": 2034,
    "name": "Миксер планетарный",
    "category": "Оборудование для кухни",
    "brand": "KitchenAid",
    "model": "5KSM7990X Professional",
    "price_pln": 5500,
    "supplier": "Gastro-Serwis",
    "image": null,
    "specs": "6.9 л, 325 Вт, 10 скоростей, для теста и кремов"
  },
  {
    "id": 2035,
    "name": "Система обратного осмоса",
    "category": "Водоподготовка",
    "brand": "BWT",
    "model": "Bestmax Premium M",
    "price_pln": 2800,
    "supplier": "BWT Polska",
    "image": null,
    "specs": "Ресурс 3800 л, Mg2+ технология, для эспрессо, фильтрация 0.0001 мкм"
  },
  {
    "id": 2036,
    "name": "Фильтр для воды картриджный",
    "category": "Водоподготовка",
    "brand": "BWT",
    "model": "Bestmax V",
    "price_pln": 1200,
    "supplier": "BWT Polska",
    "image": null,
    "specs": "Ресурс 4200 л, снижение жёсткости, защита от накипи"
  },
  {
    "id": 2037,
    "name": "Умягчитель воды",
    "category": "Водоподготовка",
    "brand": "BWT",
    "model": "Besthead FLEX",
    "price_pln": 650,
    "supplier": "BWT Polska",
    "image": null,
    "specs": "Головка подключения, байпас, манометр, быстросъём"
  },
  {
    "id": 2038,
    "name": "Фильтр для воды проточный",
    "category": "Водоподготовка",
    "brand": "Everpure",
    "model": "4C2",
    "price_pln": 900,
    "supplier": "Gastro-Serwis",
    "image": null,
    "specs": "Ресурс 11350 л, 0.5 мкм, удаление хлора и запахов"
  }
]
